README.md
scraping_subsystem/airflow_python_callables.py
scraping_subsystem/kafka_handler/kafka_handler.py
scraping_subsystem/scraper/__init__.py
scraping_subsystem/scraper/items.py
scraping_subsystem/scraper/middlewares.py
scraping_subsystem/scraper/pipelines.py
scraping_subsystem/scraper/settings.py
scraping_subsystem/scraper/spiders/__init__.py
scraping_subsystem/scraper/spiders/flamp_spider.py
scraping_subsystem/scraper/spiders/generator_start_urls.py
scraping_subsystem/scraper/spiders/test_spider.py
scraping_subsystem/scrapy.cfg
scraping_subsystem/sentiment_analyzer/analyzer.py
scraping_subsystem/sentiment_analyzer/text_cleaner.py
scrapingsubsystem-0.1.7.dist-info/METADATA
scrapingsubsystem-0.1.7.dist-info/WHEEL
scrapingsubsystem-0.1.7.dist-info/RECORD
