Metadata-Version: 2.1
Name: scrapingsubsystem
Version: 0.1.7
Summary: scraping subsystem library for airflow
Author: DieNice
Author-email: DailyPlanning@bk.ru
Requires-Python: ==3.10.*
Classifier: Programming Language :: Python :: 3
Classifier: Programming Language :: Python :: 3.10
Requires-Dist: Scrapy (>=2.6.1,<3.0.0)
Requires-Dist: bs4 (>=0.0.1,<0.0.2)
Requires-Dist: dostoevsky (>=0.6.0,<0.7.0)
Requires-Dist: fasttext (>=0.9.2,<0.10.0)
Requires-Dist: kafka-python (>=2.0.2,<3.0.0)
Requires-Dist: nltk (>=3.7,<4.0)
Requires-Dist: pandas (>=1.3.2,<2.0.0)
